{
  "recentFiles": [
    {
      "basename": "Graphs",
      "path": "Graphs.md"
    },
    {
      "basename": "Dynamic Arrays",
      "path": "Data Structures/Dynamic Arrays.md"
    },
    {
      "basename": "Priority Queue",
      "path": "Data Structures/Priority Queue.md"
    },
    {
      "basename": "Abstract Data Type",
      "path": "Data Structures/Abstract Data Type.md"
    },
    {
      "basename": "Analysis of Algorithms",
      "path": "Data Structures/Analysis of Algorithms.md"
    },
    {
      "basename": "Decrease and Conquer",
      "path": "Data Structures/Decrease and Conquer.md"
    },
    {
      "basename": "Divide and Conquer",
      "path": "Data Structures/Divide and Conquer.md"
    },
    {
      "basename": "Recursion",
      "path": "Data Structures/Recursion.md"
    },
    {
      "basename": "Brute Force",
      "path": "Data Structures/Brute Force.md"
    },
    {
      "basename": "README",
      "path": "README.md"
    },
    {
      "basename": "TODO's",
      "path": "TODO's.md"
    },
    {
      "basename": "Functions of Several Variables",
      "path": "Vector Calculus/Functions of Several Variables.md"
    },
    {
      "basename": "Limits and Continuity",
      "path": "Vector Calculus/Limits and Continuity.md"
    },
    {
      "basename": "Project 1",
      "path": "Embedded Systems/Project 1.md"
    },
    {
      "basename": "Sieve of Eratosthenes",
      "path": "Data Structures/Sieve of Eratosthenes.md"
    },
    {
      "basename": "Euclidean Algorithm",
      "path": "Discrete Structures/Euclidean Algorithm.md"
    },
    {
      "basename": "Algorithms",
      "path": "Data Structures/Algorithms.md"
    },
    {
      "basename": "Project 0",
      "path": "Electrical Lab/Project 0.md"
    },
    {
      "basename": "Level Curve",
      "path": "Vector Calculus/Definitions/Level Curve.md"
    },
    {
      "basename": "Overview",
      "path": "Vector Calculus/Overview.md"
    },
    {
      "basename": "Graph Settings",
      "path": "Graph Settings.md"
    },
    {
      "basename": "First Day",
      "path": "Embedded Systems/First Day.md"
    }
  ],
  "omittedPaths": [],
  "maxLength": null,
  "openType": "tab"
}